Metadata-Version: 1.0
Name: horo
Version: 1.2.0
Summary: A program that displays your horoscope right from the terminal
Home-page: UNKNOWN
Author: George Munyoro
Author-email: george.guva@outlook.com
License: MIT
Platform: UNKNOWN
